{
    "description": "",
    "tags": [],
    "size": {
        "height": 717,
        "width": 1001
    },
    "objects": [
        {
            "id": 651603794,
            "classId": 2876689,
            "description": "",
            "geometryType": "line",
            "labelerLogin": "danielriege",
            "createdAt": "2021-04-09T14:47:54.756Z",
            "updatedAt": "2021-04-27T09:20:17.108Z",
            "tags": [],
            "classTitle": "outer_r",
            "points": {
                "exterior": [
                    [
                        671,
                        713
                    ],
                    [
                        539,
                        568
                    ],
                    [
                        471,
                        523
                    ],
                    [
                        380,
                        481
                    ],
                    [
                        306,
                        465
                    ],
                    [
                        219,
                        453
                    ],
                    [
                        112,
                        449
                    ]
                ],
                "interior": []
            }
        },
        {
            "id": 651662770,
            "classId": 2876710,
            "description": "",
            "geometryType": "line",
            "labelerLogin": "danielriege",
            "createdAt": "2021-04-10T10:23:03.706Z",
            "updatedAt": "2021-04-27T09:20:17.108Z",
            "tags": [],
            "classTitle": "outer_l",
            "points": {
                "exterior": [
                    [
                        3,
                        615
                    ],
                    [
                        54,
                        569
                    ],
                    [
                        84,
                        537
                    ],
                    [
                        92,
                        508
                    ],
                    [
                        75,
                        493
                    ],
                    [
                        43,
                        486
                    ],
                    [
                        0,
                        477
                    ]
                ],
                "interior": []
            }
        },
        {
            "id": 698057221,
            "classId": 2907069,
            "description": "",
            "geometryType": "line",
            "labelerLogin": "danielriege",
            "createdAt": "2021-04-27T09:20:17.027Z",
            "updatedAt": "2021-04-27T09:20:23.629Z",
            "tags": [],
            "classTitle": "guide_lane",
            "points": {
                "exterior": [
                    [
                        256,
                        716
                    ],
                    [
                        300,
                        588
                    ],
                    [
                        290,
                        530
                    ],
                    [
                        258,
                        491
                    ],
                    [
                        218,
                        476
                    ],
                    [
                        174,
                        466
                    ],
                    [
                        116,
                        462
                    ],
                    [
                        3,
                        455
                    ]
                ],
                "interior": []
            }
        }
    ]
}